<?xml version="1.0" encoding="utf-8" ?>
<dwsync>
<file name="10_wok.jpg" server="nbf.z1q.ru" local="130814705197319289" remote="130735775400000000" Dst="0" />
<file name="10_wok_s.jpg" server="nbf.z1q.ru" local="130814705198249342" remote="130735767000000000" Dst="0" />
<file name="10_wok_h.jpg" server="nbf.z1q.ru" local="130814705199009385" remote="130735767000000000" Dst="0" />
<file name="1_wok_s.jpg" server="nbf.z1q.ru" local="130814705201079504" remote="130386132000000000" Dst="0" />
<file name="1_wok_h.jpg" server="nbf.z1q.ru" local="130814705201859548" remote="130386132000000000" Dst="0" />
<file name="1_wok.jpg" server="nbf.z1q.ru" local="130814705202909608" remote="130386132000000000" Dst="0" />
<file name="2_wok.jpg" server="nbf.z1q.ru" local="130814705204429695" remote="130386132000000000" Dst="0" />
<file name="2_wok_s.jpg" server="nbf.z1q.ru" local="130814705204999728" remote="130386132000000000" Dst="0" />
<file name="2_wok_h.jpg" server="nbf.z1q.ru" local="130814705205819775" remote="130386132000000000" Dst="0" />
<file name="3_wok.jpg" server="nbf.z1q.ru" local="130814705207969898" remote="130386132000000000" Dst="0" />
<file name="3_wok_h.jpg" server="nbf.z1q.ru" local="130814705208729941" remote="130386132000000000" Dst="0" />
<file name="4_wok_h.jpg" server="nbf.z1q.ru" local="130814705209990013" remote="130386132000000000" Dst="0" />
<file name="4_wok_s.jpg" server="nbf.z1q.ru" local="130814705211600105" remote="130386132000000000" Dst="0" />
<file name="5_wok_h.jpg" server="nbf.z1q.ru" local="130814705213890236" remote="130386132000000000" Dst="0" />
<file name="5_wok.jpg" server="nbf.z1q.ru" local="130814705214860292" remote="130386132000000000" Dst="0" />
<file name="5_wok_s.jpg" server="nbf.z1q.ru" local="130814705215500329" remote="130386132000000000" Dst="0" />
<file name="6_wok_s.jpg" server="nbf.z1q.ru" local="130814705218480499" remote="130386132000000000" Dst="0" />
<file name="6_wok.jpg" server="nbf.z1q.ru" local="130814705220250600" remote="130386132000000000" Dst="0" />
<file name="6_wok_h.jpg" server="nbf.z1q.ru" local="130814705220890637" remote="130386132000000000" Dst="0" />
<file name="3_wok_s.jpg" server="nbf.z1q.ru" local="130814705223040760" remote="130386132000000000" Dst="0" />
<file name="4_wok.jpg" server="nbf.z1q.ru" local="130814705223900809" remote="130386132000000000" Dst="0" />
<file name="7_wok_s.jpg" server="nbf.z1q.ru" local="130814705224630851" remote="130386132000000000" Dst="0" />
<file name="7_wok_h.jpg" server="nbf.z1q.ru" local="130814705225870922" remote="130386132000000000" Dst="0" />
<file name="7_wok.jpg" server="nbf.z1q.ru" local="130814705226040931" remote="130386132000000000" Dst="0" />
<file name="8_wok_s.jpg" server="nbf.z1q.ru" local="130814705228581077" remote="130386132000000000" Dst="0" />
<file name="8_wok_h.jpg" server="nbf.z1q.ru" local="130814705229351121" remote="130386132000000000" Dst="0" />
<file name="8_wok.jpg" server="nbf.z1q.ru" local="130814705230241172" remote="130386132000000000" Dst="0" />
<file name="9_wok.jpg" server="nbf.z1q.ru" local="130814705230781203" remote="130735776600000000" Dst="0" />
<file name="9_wok_h.jpg" server="nbf.z1q.ru" local="130814705232211284" remote="130735767000000000" Dst="0" />
<file name="9_wok_s.jpg" server="nbf.z1q.ru" local="130814705232841320" remote="130735767000000000" Dst="0" />
<file name="osnova.jpg" server="nbf.z1q.ru" local="130814705241521817" remote="130386132000000000" Dst="0" />
</dwsync>